electricalsim_opf_quadratic/__init__.py
electricalsim_opf_quadratic/extension.py
electricalsim_opf_quadratic/input.ui
electricalsim_opf_quadratic-1.3.dist-info/METADATA
electricalsim_opf_quadratic-1.3.dist-info/WHEEL
electricalsim_opf_quadratic-1.3.dist-info/entry_points.txt
electricalsim_opf_quadratic-1.3.dist-info/licenses/LICENSE
electricalsim_opf_quadratic-1.3.dist-info/RECORD
